{
    "'s": [
        1,
        {
            "1267": 1
        }
    ],
    "1": [
        1,
        {
            "1267": 1
        }
    ],
    "14": [
        1,
        {
            "1267": 3
        }
    ],
    "201": [
        1,
        {
            "1267": 2
        }
    ],
    "2020": [
        1,
        {
            "1267": 6
        }
    ],
    "203": [
        1,
        {
            "1267": 2
        }
    ],
    "210": [
        1,
        {
            "1267": 1
        }
    ],
    "221": [
        1,
        {
            "1267": 2
        }
    ],
    "222": [
        1,
        {
            "1267": 2
        }
    ],
    "271": [
        1,
        {
            "1267": 1
        }
    ],
    "364": [
        1,
        {
            "1267": 1
        }
    ],
    "a": [
        1,
        {
            "1267": 17
        }
    ],
    "aboriginal": [
        1,
        {
            "1267": 2
        }
    ],
    "academic": [
        1,
        {
            "1267": 5
        }
    ],
    "acco": [
        1,
        {
            "1267": 1
        }
    ],
    "accounting": [
        1,
        {
            "1267": 1
        }
    ],
    "activities": [
        1,
        {
            "1267": 3
        }
    ],
    "advocacy": [
        1,
        {
            "1267": 4
        }
    ],
    "all": [
        1,
        {
            "1267": 3
        }
    ],
    "also": [
        1,
        {
            "1267": 4
        }
    ],
    "and": [
        1,
        {
            "1267": 85
        }
    ],
    "answer": [
        1,
        {
            "1267": 1
        }
    ],
    "any": [
        1,
        {
            "1267": 5
        }
    ],
    "appointments": [
        1,
        {
            "1267": 7
        }
    ],
    "are": [
        1,
        {
            "1267": 14
        }
    ],
    "as": [
        1,
        {
            "1267": 12
        }
    ],
    "asrc": [
        1,
        {
            "1267": 2
        }
    ],
    "assignments": [
        1,
        {
            "1267": 1
        }
    ],
    "assistance": [
        1,
        {
            "1267": 3
        }
    ],
    "assistants": [
        1,
        {
            "1267": 1
        }
    ],
    "at": [
        1,
        {
            "1267": 9
        }
    ],
    "attend": [
        1,
        {
            "1267": 2
        }
    ],
    "available": [
        1,
        {
            "1267": 10
        }
    ],
    "balance": [
        1,
        {
            "1267": 1
        }
    ],
    "be": [
        1,
        {
            "1267": 7
        }
    ],
    "beginning": [
        1,
        {
            "1267": 1
        }
    ],
    "best": [
        1,
        {
            "1267": 1
        }
    ],
    "bio": [
        1,
        {
            "1267": 2
        }
    ],
    "both": [
        1,
        {
            "1267": 2
        }
    ],
    "by": [
        1,
        {
            "1267": 9
        }
    ],
    "capabilities": [
        1,
        {
            "1267": 2
        }
    ],
    "career": [
        1,
        {
            "1267": 6
        }
    ],
    "centre": [
        1,
        {
            "1267": 23
        }
    ],
    "chat": [
        1,
        {
            "1267": 1
        }
    ],
    "chats": [
        1,
        {
            "1267": 1
        }
    ],
    "check": [
        1,
        {
            "1267": 4
        }
    ],
    "chem": [
        1,
        {
            "1267": 2
        }
    ],
    "class": [
        1,
        {
            "1267": 1
        }
    ],
    "code": [
        1,
        {
            "1267": 2
        }
    ],
    "collaboration": [
        1,
        {
            "1267": 1
        }
    ],
    "collaborative": [
        1,
        {
            "1267": 1
        }
    ],
    "comm": [
        1,
        {
            "1267": 1
        }
    ],
    "communicating": [
        1,
        {
            "1267": 1
        }
    ],
    "communication": [
        1,
        {
            "1267": 2
        }
    ],
    "community": [
        1,
        {
            "1267": 3
        }
    ],
    "concordia": [
        1,
        {
            "1267": 10
        }
    ],
    "concordia.ca": [
        1,
        {
            "1267": 8
        }
    ],
    "conduct": [
        1,
        {
            "1267": 1
        }
    ],
    "confidential": [
        1,
        {
            "1267": 1
        }
    ],
    "connecting": [
        1,
        {
            "1267": 2
        }
    ],
    "continue": [
        1,
        {
            "1267": 2
        }
    ],
    "conversation": [
        1,
        {
            "1267": 3
        }
    ],
    "counselling": [
        1,
        {
            "1267": 9
        }
    ],
    "course": [
        1,
        {
            "1267": 1
        }
    ],
    "courses": [
        1,
        {
            "1267": 2
        }
    ],
    "covering": [
        1,
        {
            "1267": 1
        }
    ],
    "crew": [
        1,
        {
            "1267": 2
        }
    ],
    "current": [
        1,
        {
            "1267": 1
        }
    ],
    "december": [
        1,
        {
            "1267": 1
        }
    ],
    "designed": [
        1,
        {
            "1267": 1
        }
    ],
    "development": [
        1,
        {
            "1267": 6
        }
    ],
    "digital": [
        1,
        {
            "1267": 2
        }
    ],
    "econ": [
        1,
        {
            "1267": 3
        }
    ],
    "effectively": [
        1,
        {
            "1267": 1
        }
    ],
    "either": [
        1,
        {
            "1267": 1
        }
    ],
    "email": [
        1,
        {
            "1267": 10
        }
    ],
    "english": [
        1,
        {
            "1267": 5
        }
    ],
    "entrepreneurship": [
        1,
        {
            "1267": 2
        }
    ],
    "esl": [
        1,
        {
            "1267": 1
        }
    ],
    "events": [
        1,
        {
            "1267": 5
        }
    ],
    "exam": [
        1,
        {
            "1267": 1
        }
    ],
    "exams": [
        1,
        {
            "1267": 2
        }
    ],
    "facebook": [
        1,
        {
            "1267": 4
        }
    ],
    "facilitated": [
        1,
        {
            "1267": 3
        }
    ],
    "fall": [
        1,
        {
            "1267": 4
        }
    ],
    "finish": [
        1,
        {
            "1267": 1
        }
    ],
    "first-year": [
        1,
        {
            "1267": 1
        }
    ],
    "focus": [
        1,
        {
            "1267": 1
        }
    ],
    "for": [
        1,
        {
            "1267": 25
        }
    ],
    "formats": [
        1,
        {
            "1267": 1
        }
    ],
    "french": [
        1,
        {
            "1267": 5
        }
    ],
    "futureready": [
        1,
        {
            "1267": 3
        }
    ],
    "geog": [
        1,
        {
            "1267": 1
        }
    ],
    "get": [
        1,
        {
            "1267": 2
        }
    ],
    "getting": [
        1,
        {
            "1267": 1
        }
    ],
    "gradproskills": [
        1,
        {
            "1267": 2
        }
    ],
    "graduate": [
        1,
        {
            "1267": 5
        }
    ],
    "great": [
        1,
        {
            "1267": 2
        }
    ],
    "group": [
        1,
        {
            "1267": 7
        }
    ],
    "groups": [
        1,
        {
            "1267": 5
        }
    ],
    "growth": [
        1,
        {
            "1267": 1
        }
    ],
    "guidance": [
        1,
        {
            "1267": 1
        }
    ],
    "hacks": [
        1,
        {
            "1267": 1
        }
    ],
    "handouts": [
        1,
        {
            "1267": 2
        }
    ],
    "has": [
        1,
        {
            "1267": 1
        }
    ],
    "healthy": [
        1,
        {
            "1267": 5
        }
    ],
    "help": [
        1,
        {
            "1267": 8
        }
    ],
    "how": [
        1,
        {
            "1267": 5
        }
    ],
    "in": [
        1,
        {
            "1267": 12
        }
    ],
    "includes": [
        1,
        {
            "1267": 1
        }
    ],
    "increase": [
        1,
        {
            "1267": 1
        }
    ],
    "innovation": [
        1,
        {
            "1267": 2
        }
    ],
    "integrity": [
        1,
        {
            "1267": 1
        }
    ],
    "interactive": [
        1,
        {
            "1267": 1
        }
    ],
    "is": [
        1,
        {
            "1267": 7
        }
    ],
    "leadership": [
        1,
        {
            "1267": 2
        }
    ],
    "learn": [
        1,
        {
            "1267": 1
        }
    ],
    "learning": [
        1,
        {
            "1267": 13
        }
    ],
    "lectures": [
        1,
        {
            "1267": 1
        }
    ],
    "led": [
        1,
        {
            "1267": 1
        }
    ],
    "life": [
        1,
        {
            "1267": 1
        }
    ],
    "live": [
        1,
        {
            "1267": 4
        }
    ],
    "managing": [
        1,
        {
            "1267": 1
        }
    ],
    "math": [
        1,
        {
            "1267": 6
        }
    ],
    "math-based": [
        1,
        {
            "1267": 1
        }
    ],
    "mentors": [
        1,
        {
            "1267": 3
        }
    ],
    "mock": [
        1,
        {
            "1267": 2
        }
    ],
    "navigate": [
        1,
        {
            "1267": 1
        }
    ],
    "networking": [
        1,
        {
            "1267": 2
        }
    ],
    "new": [
        1,
        {
            "1267": 10
        }
    ],
    "note-taking": [
        1,
        {
            "1267": 1
        }
    ],
    "november/december": [
        1,
        {
            "1267": 1
        }
    ],
    "of": [
        1,
        {
            "1267": 13
        }
    ],
    "offered": [
        1,
        {
            "1267": 5
        }
    ],
    "offering": [
        1,
        {
            "1267": 2
        }
    ],
    "offers": [
        1,
        {
            "1267": 1
        }
    ],
    "office": [
        1,
        {
            "1267": 7
        }
    ],
    "on-demand": [
        1,
        {
            "1267": 1
        }
    ],
    "one-on-one": [
        1,
        {
            "1267": 5
        }
    ],
    "online": [
        1,
        {
            "1267": 14
        }
    ],
    "online/remote": [
        1,
        {
            "1267": 1
        }
    ],
    "opportunities": [
        1,
        {
            "1267": 4
        }
    ],
    "or": [
        1,
        {
            "1267": 19
        }
    ],
    "organized": [
        1,
        {
            "1267": 1
        }
    ],
    "orientation": [
        1,
        {
            "1267": 2
        }
    ],
    "our": [
        1,
        {
            "1267": 8
        }
    ],
    "out": [
        1,
        {
            "1267": 5
        }
    ],
    "over": [
        1,
        {
            "1267": 4
        }
    ],
    "participating": [
        1,
        {
            "1267": 1
        }
    ],
    "peer": [
        1,
        {
            "1267": 3
        }
    ],
    "phone": [
        1,
        {
            "1267": 6
        }
    ],
    "practice": [
        1,
        {
            "1267": 2
        }
    ],
    "process": [
        1,
        {
            "1267": 1
        }
    ],
    "professional": [
        1,
        {
            "1267": 2
        }
    ],
    "program": [
        1,
        {
            "1267": 2
        }
    ],
    "promote": [
        1,
        {
            "1267": 1
        }
    ],
    "questions": [
        1,
        {
            "1267": 6
        }
    ],
    "reaching": [
        1,
        {
            "1267": 1
        }
    ],
    "read": [
        1,
        {
            "1267": 1
        }
    ],
    "readings": [
        1,
        {
            "1267": 1
        }
    ],
    "regular": [
        1,
        {
            "1267": 1
        }
    ],
    "regulations": [
        1,
        {
            "1267": 1
        }
    ],
    "remember": [
        1,
        {
            "1267": 1
        }
    ],
    "remotely": [
        1,
        {
            "1267": 2
        }
    ],
    "requiring": [
        1,
        {
            "1267": 1
        }
    ],
    "research": [
        1,
        {
            "1267": 1
        }
    ],
    "resource": [
        1,
        {
            "1267": 4
        }
    ],
    "resources": [
        1,
        {
            "1267": 5
        }
    ],
    "responsibilities": [
        1,
        {
            "1267": 1
        }
    ],
    "resume": [
        1,
        {
            "1267": 4
        }
    ],
    "review": [
        1,
        {
            "1267": 1
        }
    ],
    "rights": [
        1,
        {
            "1267": 1
        }
    ],
    "rules": [
        1,
        {
            "1267": 1
        }
    ],
    "self-development": [
        1,
        {
            "1267": 1
        }
    ],
    "semester": [
        1,
        {
            "1267": 1
        }
    ],
    "september": [
        1,
        {
            "1267": 4
        }
    ],
    "series": [
        1,
        {
            "1267": 2
        }
    ],
    "services": [
        1,
        {
            "1267": 23
        }
    ],
    "session": [
        1,
        {
            "1267": 1
        }
    ],
    "sessions": [
        1,
        {
            "1267": 12
        }
    ],
    "setting": [
        1,
        {
            "1267": 1
        }
    ],
    "skills": [
        1,
        {
            "1267": 8
        }
    ],
    "specialist": [
        1,
        {
            "1267": 3
        }
    ],
    "specifically": [
        1,
        {
            "1267": 1
        }
    ],
    "staff": [
        1,
        {
            "1267": 4
        }
    ],
    "stage": [
        1,
        {
            "1267": 1
        }
    ],
    "stay": [
        1,
        {
            "1267": 3
        }
    ],
    "strategic": [
        1,
        {
            "1267": 2
        }
    ],
    "strategies": [
        1,
        {
            "1267": 1
        }
    ],
    "student": [
        1,
        {
            "1267": 24
        }
    ],
    "students": [
        1,
        {
            "1267": 21
        }
    ],
    "study": [
        1,
        {
            "1267": 4
        }
    ],
    "success": [
        1,
        {
            "1267": 3
        }
    ],
    "successfully": [
        1,
        {
            "1267": 2
        }
    ],
    "such": [
        1,
        {
            "1267": 1
        }
    ],
    "support": [
        1,
        {
            "1267": 14
        }
    ],
    "telephone": [
        1,
        {
            "1267": 1
        }
    ],
    "term": [
        1,
        {
            "1267": 2
        }
    ],
    "the": [
        1,
        {
            "1267": 24
        }
    ],
    "these": [
        1,
        {
            "1267": 3
        }
    ],
    "they": [
        1,
        {
            "1267": 1
        }
    ],
    "this": [
        1,
        {
            "1267": 4
        }
    ],
    "through": [
        1,
        {
            "1267": 8
        }
    ],
    "time": [
        1,
        {
            "1267": 3
        }
    ],
    "tips": [
        1,
        {
            "1267": 2
        }
    ],
    "to": [
        1,
        {
            "1267": 38
        }
    ],
    "transition": [
        1,
        {
            "1267": 2
        }
    ],
    "tutoring": [
        1,
        {
            "1267": 1
        }
    ],
    "undergraduate": [
        1,
        {
            "1267": 4
        }
    ],
    "undergraduates": [
        1,
        {
            "1267": 1
        }
    ],
    "university": [
        1,
        {
            "1267": 5
        }
    ],
    "until": [
        1,
        {
            "1267": 1
        }
    ],
    "via": [
        1,
        {
            "1267": 9
        }
    ],
    "videos": [
        1,
        {
            "1267": 3
        }
    ],
    "virtual": [
        1,
        {
            "1267": 19
        }
    ],
    "virtually": [
        1,
        {
            "1267": 3
        }
    ],
    "ways": [
        1,
        {
            "1267": 1
        }
    ],
    "welcome": [
        1,
        {
            "1267": 2
        }
    ],
    "well": [
        1,
        {
            "1267": 6
        }
    ],
    "well-being": [
        1,
        {
            "1267": 1
        }
    ],
    "will": [
        1,
        {
            "1267": 7
        }
    ],
    "with": [
        1,
        {
            "1267": 19
        }
    ],
    "working": [
        1,
        {
            "1267": 2
        }
    ],
    "workshops": [
        1,
        {
            "1267": 6
        }
    ],
    "writing": [
        1,
        {
            "1267": 9
        }
    ],
    "your": [
        1,
        {
            "1267": 9
        }
    ],
    "zoom": [
        1,
        {
            "1267": 10
        }
    ]
}