{
    "'s": [
        1,
        {
            "967": 1
        }
    ],
    "1": [
        1,
        {
            "967": 1
        }
    ],
    "12:00": [
        1,
        {
            "966": 1
        }
    ],
    "170": [
        1,
        {
            "966": 2
        }
    ],
    "1:00": [
        1,
        {
            "966": 1
        }
    ],
    "2": [
        1,
        {
            "966": 1
        }
    ],
    "3702": [
        1,
        {
            "966": 1
        }
    ],
    "4:00": [
        1,
        {
            "966": 1
        }
    ],
    "514-848-3717": [
        2,
        {
            "966": 1,
            "967": 2
        }
    ],
    "7": [
        1,
        {
            "967": 1
        }
    ],
    "911": [
        1,
        {
            "967": 1
        }
    ],
    "9:00": [
        1,
        {
            "966": 2
        }
    ],
    "a": [
        2,
        {
            "966": 2,
            "967": 9
        }
    ],
    "a.m.": [
        1,
        {
            "966": 3
        }
    ],
    "able": [
        1,
        {
            "967": 1
        }
    ],
    "accepting": [
        1,
        {
            "967": 1
        }
    ],
    "access": [
        2,
        {
            "966": 13,
            "967": 1
        }
    ],
    "accompaniment": [
        1,
        {
            "967": 2
        }
    ],
    "accompaniments": [
        1,
        {
            "967": 1
        }
    ],
    "after": [
        1,
        {
            "967": 1
        }
    ],
    "all": [
        2,
        {
            "966": 2,
            "967": 3
        }
    ],
    "allows": [
        1,
        {
            "967": 1
        }
    ],
    "along": [
        1,
        {
            "966": 1
        }
    ],
    "an": [
        1,
        {
            "967": 1
        }
    ],
    "and": [
        2,
        {
            "966": 5,
            "967": 8
        }
    ],
    "another": [
        1,
        {
            "967": 1
        }
    ],
    "any": [
        1,
        {
            "967": 2
        }
    ],
    "application": [
        1,
        {
            "967": 1
        }
    ],
    "appointments": [
        1,
        {
            "967": 1
        }
    ],
    "are": [
        2,
        {
            "966": 3,
            "967": 4
        }
    ],
    "area": [
        1,
        {
            "967": 3
        }
    ],
    "arrival": [
        1,
        {
            "967": 1
        }
    ],
    "as": [
        2,
        {
            "966": 1,
            "967": 8
        }
    ],
    "assistance": [
        1,
        {
            "966": 1
        }
    ],
    "at": [
        2,
        {
            "966": 8,
            "967": 3
        }
    ],
    "available": [
        1,
        {
            "967": 2
        }
    ],
    "be": [
        2,
        {
            "966": 8,
            "967": 2
        }
    ],
    "being": [
        1,
        {
            "967": 1
        }
    ],
    "below": [
        1,
        {
            "967": 1
        }
    ],
    "both": [
        1,
        {
            "967": 2
        }
    ],
    "boxes": [
        1,
        {
            "967": 1
        }
    ],
    "by": [
        2,
        {
            "966": 4,
            "967": 2
        }
    ],
    "call": [
        1,
        {
            "967": 2
        }
    ],
    "calling": [
        1,
        {
            "966": 1
        }
    ],
    "campus": [
        2,
        {
            "966": 6,
            "967": 6
        }
    ],
    "campuses": [
        1,
        {
            "967": 2
        }
    ],
    "can": [
        2,
        {
            "966": 1,
            "967": 4
        }
    ],
    "card": [
        1,
        {
            "966": 7
        }
    ],
    "cards": [
        1,
        {
            "966": 3
        }
    ],
    "cellphone": [
        1,
        {
            "967": 2
        }
    ],
    "chooses": [
        1,
        {
            "967": 1
        }
    ],
    "community": [
        1,
        {
            "967": 4
        }
    ],
    "concordia": [
        2,
        {
            "966": 4,
            "967": 4
        }
    ],
    "concordia.ca": [
        1,
        {
            "966": 6
        }
    ],
    "contact": [
        2,
        {
            "966": 4,
            "967": 3
        }
    ],
    "coordinate": [
        1,
        {
            "967": 1
        }
    ],
    "coordinated": [
        1,
        {
            "966": 1
        }
    ],
    "day": [
        1,
        {
            "967": 1
        }
    ],
    "days": [
        1,
        {
            "967": 1
        }
    ],
    "de": [
        1,
        {
            "967": 3
        }
    ],
    "deactivate": [
        1,
        {
            "967": 1
        }
    ],
    "department": [
        1,
        {
            "966": 5
        }
    ],
    "departments": [
        1,
        {
            "967": 1
        }
    ],
    "departure": [
        1,
        {
            "967": 1
        }
    ],
    "devices": [
        1,
        {
            "967": 1
        }
    ],
    "dialed": [
        1,
        {
            "967": 1
        }
    ],
    "dispatcher": [
        1,
        {
            "967": 1
        }
    ],
    "do": [
        1,
        {
            "967": 1
        }
    ],
    "does": [
        1,
        {
            "967": 2
        }
    ],
    "duration": [
        1,
        {
            "967": 1
        }
    ],
    "during": [
        1,
        {
            "967": 1
        }
    ],
    "email": [
        1,
        {
            "966": 1
        }
    ],
    "emailing": [
        1,
        {
            "966": 1
        }
    ],
    "emergency": [
        1,
        {
            "967": 2
        }
    ],
    "even": [
        1,
        {
            "967": 1
        }
    ],
    "exact": [
        1,
        {
            "967": 1
        }
    ],
    "ext": [
        1,
        {
            "966": 1
        }
    ],
    "facebook": [
        1,
        {
            "967": 1
        }
    ],
    "facilities": [
        1,
        {
            "966": 2
        }
    ],
    "faculty": [
        1,
        {
            "967": 1
        }
    ],
    "feature": [
        1,
        {
            "967": 1
        }
    ],
    "feel": [
        1,
        {
            "967": 2
        }
    ],
    "for": [
        2,
        {
            "966": 9,
            "967": 3
        }
    ],
    "forget": [
        1,
        {
            "967": 1
        }
    ],
    "forwarded": [
        1,
        {
            "966": 1
        }
    ],
    "friday": [
        1,
        {
            "966": 3
        }
    ],
    "from": [
        2,
        {
            "966": 5,
            "967": 1
        }
    ],
    "george": [
        1,
        {
            "967": 1
        }
    ],
    "get": [
        1,
        {
            "967": 1
        }
    ],
    "guardian": [
        1,
        {
            "967": 4
        }
    ],
    "harassed": [
        1,
        {
            "967": 1
        }
    ],
    "has": [
        1,
        {
            "967": 1
        }
    ],
    "have": [
        1,
        {
            "967": 4
        }
    ],
    "help": [
        1,
        {
            "967": 1
        }
    ],
    "hours": [
        2,
        {
            "966": 7,
            "967": 1
        }
    ],
    "how": [
        1,
        {
            "967": 1
        }
    ],
    "if": [
        1,
        {
            "967": 7
        }
    ],
    "immediately": [
        2,
        {
            "966": 1,
            "967": 1
        }
    ],
    "in": [
        1,
        {
            "966": 2
        }
    ],
    "indicating": [
        1,
        {
            "967": 1
        }
    ],
    "individuals": [
        2,
        {
            "966": 2,
            "967": 1
        }
    ],
    "inform": [
        1,
        {
            "967": 1
        }
    ],
    "information": [
        1,
        {
            "966": 5
        }
    ],
    "is": [
        1,
        {
            "967": 4
        }
    ],
    "isolation": [
        1,
        {
            "966": 1
        }
    ],
    "it": [
        1,
        {
            "967": 1
        }
    ],
    "key": [
        1,
        {
            "966": 5
        }
    ],
    "keyctrl": [
        1,
        {
            "966": 1
        }
    ],
    "keys": [
        1,
        {
            "966": 2
        }
    ],
    "khan": [
        1,
        {
            "966": 1
        }
    ],
    "la": [
        1,
        {
            "967": 1
        }
    ],
    "linkedin": [
        1,
        {
            "967": 1
        }
    ],
    "local": [
        1,
        {
            "967": 1
        }
    ],
    "location": [
        1,
        {
            "967": 3
        }
    ],
    "long": [
        1,
        {
            "967": 2
        }
    ],
    "longer": [
        1,
        {
            "967": 1
        }
    ],
    "loss": [
        1,
        {
            "966": 1
        }
    ],
    "lost": [
        1,
        {
            "966": 1
        }
    ],
    "loyola": [
        2,
        {
            "966": 2,
            "967": 3
        }
    ],
    "made": [
        1,
        {
            "966": 1
        }
    ],
    "make": [
        1,
        {
            "967": 1
        }
    ],
    "management": [
        1,
        {
            "966": 2
        }
    ],
    "maps": [
        1,
        {
            "967": 1
        }
    ],
    "may": [
        2,
        {
            "966": 3,
            "967": 2
        }
    ],
    "members": [
        1,
        {
            "967": 3
        }
    ],
    "members\u2014including": [
        1,
        {
            "967": 1
        }
    ],
    "message": [
        1,
        {
            "967": 1
        }
    ],
    "mobile": [
        1,
        {
            "967": 1
        }
    ],
    "monday": [
        1,
        {
            "966": 3
        }
    ],
    "moniter": [
        1,
        {
            "967": 1
        }
    ],
    "montr\u00e9al": [
        1,
        {
            "967": 1
        }
    ],
    "more": [
        1,
        {
            "966": 3
        }
    ],
    "must": [
        1,
        {
            "966": 3
        }
    ],
    "n't": [
        1,
        {
            "967": 1
        }
    ],
    "not": [
        1,
        {
            "967": 1
        }
    ],
    "note": [
        1,
        {
            "967": 1
        }
    ],
    "of": [
        2,
        {
            "966": 6,
            "967": 5
        }
    ],
    "offers": [
        1,
        {
            "967": 1
        }
    ],
    "office": [
        1,
        {
            "966": 2
        }
    ],
    "on": [
        2,
        {
            "966": 3,
            "967": 3
        }
    ],
    "one": [
        1,
        {
            "967": 2
        }
    ],
    "online": [
        1,
        {
            "966": 1
        }
    ],
    "opening": [
        1,
        {
            "966": 1
        }
    ],
    "operation": [
        1,
        {
            "966": 3
        }
    ],
    "option": [
        2,
        {
            "966": 1,
            "967": 1
        }
    ],
    "or": [
        2,
        {
            "966": 9,
            "967": 2
        }
    ],
    "other": [
        1,
        {
            "966": 2
        }
    ],
    "our": [
        1,
        {
            "967": 2
        }
    ],
    "outline": [
        1,
        {
            "967": 1
        }
    ],
    "outside": [
        2,
        {
            "966": 1,
            "967": 1
        }
    ],
    "p.m": [
        1,
        {
            "966": 1
        }
    ],
    "p.m.": [
        1,
        {
            "966": 3
        }
    ],
    "page": [
        1,
        {
            "966": 1
        }
    ],
    "per": [
        1,
        {
            "966": 1
        }
    ],
    "person": [
        2,
        {
            "966": 1,
            "967": 2
        }
    ],
    "picked": [
        1,
        {
            "966": 1
        }
    ],
    "please": [
        2,
        {
            "966": 5,
            "967": 1
        }
    ],
    "point": [
        1,
        {
            "967": 1
        }
    ],
    "points": [
        1,
        {
            "967": 1
        }
    ],
    "police": [
        1,
        {
            "967": 2
        }
    ],
    "policy": [
        1,
        {
            "966": 1
        }
    ],
    "possible": [
        1,
        {
            "967": 1
        }
    ],
    "priorities": [
        1,
        {
            "967": 1
        }
    ],
    "provide": [
        1,
        {
            "967": 1
        }
    ],
    "pursued": [
        1,
        {
            "967": 1
        }
    ],
    "rave": [
        1,
        {
            "967": 1
        }
    ],
    "receive": [
        1,
        {
            "967": 1
        }
    ],
    "red": [
        1,
        {
            "967": 1
        }
    ],
    "relevant": [
        1,
        {
            "966": 1
        }
    ],
    "report": [
        1,
        {
            "966": 1
        }
    ],
    "request": [
        2,
        {
            "966": 4,
            "967": 1
        }
    ],
    "requests": [
        2,
        {
            "966": 4,
            "967": 1
        }
    ],
    "required": [
        1,
        {
            "967": 1
        }
    ],
    "respond": [
        1,
        {
            "967": 1
        }
    ],
    "responding": [
        1,
        {
            "967": 1
        }
    ],
    "response": [
        1,
        {
            "967": 1
        }
    ],
    "s": [
        1,
        {
            "966": 1
        }
    ],
    "safe": [
        1,
        {
            "967": 2
        }
    ],
    "safewalk": [
        1,
        {
            "967": 8
        }
    ],
    "security": [
        2,
        {
            "966": 11,
            "967": 7
        }
    ],
    "see": [
        1,
        {
            "967": 1
        }
    ],
    "service": [
        1,
        {
            "967": 8
        }
    ],
    "services": [
        2,
        {
            "966": 1,
            "967": 1
        }
    ],
    "set": [
        1,
        {
            "967": 1
        }
    ],
    "several": [
        1,
        {
            "967": 1
        }
    ],
    "sgw": [
        2,
        {
            "966": 2,
            "967": 2
        }
    ],
    "sir": [
        1,
        {
            "967": 1
        }
    ],
    "so": [
        1,
        {
            "967": 1
        }
    ],
    "soon": [
        1,
        {
            "967": 1
        }
    ],
    "sp": [
        1,
        {
            "966": 2
        }
    ],
    "sp-170": [
        1,
        {
            "966": 2
        }
    ],
    "staff": [
        1,
        {
            "967": 1
        }
    ],
    "students": [
        1,
        {
            "967": 1
        }
    ],
    "team": [
        1,
        {
            "967": 2
        }
    ],
    "text": [
        1,
        {
            "967": 1
        }
    ],
    "that": [
        1,
        {
            "967": 2
        }
    ],
    "the": [
        2,
        {
            "966": 11,
            "967": 19
        }
    ],
    "them": [
        1,
        {
            "967": 1
        }
    ],
    "these": [
        2,
        {
            "966": 1,
            "967": 1
        }
    ],
    "they": [
        1,
        {
            "967": 3
        }
    ],
    "this": [
        1,
        {
            "967": 1
        }
    ],
    "threatened": [
        1,
        {
            "967": 1
        }
    ],
    "through": [
        1,
        {
            "966": 1
        }
    ],
    "timer": [
        1,
        {
            "967": 4
        }
    ],
    "to": [
        2,
        {
            "966": 21,
            "967": 12
        }
    ],
    "travel": [
        1,
        {
            "967": 3
        }
    ],
    "treat": [
        1,
        {
            "967": 1
        }
    ],
    "twitter": [
        1,
        {
            "967": 1
        }
    ],
    "university": [
        1,
        {
            "966": 2
        }
    ],
    "unsafe": [
        1,
        {
            "967": 1
        }
    ],
    "up": [
        1,
        {
            "966": 1
        }
    ],
    "upon": [
        1,
        {
            "967": 1
        }
    ],
    "use": [
        1,
        {
            "967": 1
        }
    ],
    "user": [
        1,
        {
            "967": 1
        }
    ],
    "via": [
        1,
        {
            "967": 1
        }
    ],
    "vidya": [
        1,
        {
            "966": 1
        }
    ],
    "vidya.khan": [
        1,
        {
            "966": 1
        }
    ],
    "ville": [
        1,
        {
            "967": 1
        }
    ],
    "virtual": [
        1,
        {
            "967": 4
        }
    ],
    "visit": [
        1,
        {
            "966": 3
        }
    ],
    "visitors\u201424": [
        1,
        {
            "967": 1
        }
    ],
    "vps-6": [
        1,
        {
            "966": 1
        }
    ],
    "wait": [
        1,
        {
            "967": 1
        }
    ],
    "walk": [
        1,
        {
            "967": 1
        }
    ],
    "we": [
        1,
        {
            "967": 2
        }
    ],
    "week": [
        1,
        {
            "967": 1
        }
    ],
    "when": [
        1,
        {
            "967": 1
        }
    ],
    "while": [
        1,
        {
            "967": 2
        }
    ],
    "will": [
        1,
        {
            "967": 6
        }
    ],
    "williams": [
        1,
        {
            "967": 1
        }
    ],
    "with": [
        2,
        {
            "966": 1,
            "967": 1
        }
    ],
    "within": [
        1,
        {
            "967": 1
        }
    ],
    "work": [
        1,
        {
            "967": 1
        }
    ],
    "working": [
        1,
        {
            "966": 1
        }
    ],
    "you": [
        2,
        {
            "966": 6,
            "967": 11
        }
    ],
    "your": [
        1,
        {
            "967": 3
        }
    ],
    "\u2019": [
        1,
        {
            "966": 1
        }
    ]
}